[
    {
        "componentChunkName": "component---src-templates-blog-post-js",
        "layout": "layout---index",
        "layoutComponentChunkName": "component---src-layouts-index-js",
        "jsonName": "static-type-checking-js.json",
        "path": "/static-type-checking-js/"
    },
    {
        "componentChunkName": "component---src-templates-blog-post-js",
        "layout": "layout---index",
        "layoutComponentChunkName": "component---src-layouts-index-js",
        "jsonName": "gradient-coin-tutorial-part-3.json",
        "path": "/gradient-coin-tutorial-part-3/"
    },
    {
        "componentChunkName": "component---src-templates-blog-post-js",
        "layout": "layout---index",
        "layoutComponentChunkName": "component---src-layouts-index-js",
        "jsonName": "react-state.json",
        "path": "/react-state/"
    },
    {
        "componentChunkName": "component---src-templates-blog-post-js",
        "layout": "layout---index",
        "layoutComponentChunkName": "component---src-layouts-index-js",
        "jsonName": "gradient-coin-tutorial-part-2.json",
        "path": "/gradient-coin-tutorial-part-2/"
    },
    {
        "componentChunkName": "component---src-templates-blog-post-js",
        "layout": "layout---index",
        "layoutComponentChunkName": "component---src-layouts-index-js",
        "jsonName": "react-lifecycle-methods.json",
        "path": "/react_lifecycle_methods/"
    },
    {
        "componentChunkName": "component---src-templates-blog-post-js",
        "layout": "layout---index",
        "layoutComponentChunkName": "component---src-layouts-index-js",
        "jsonName": "javascript-type-system.json",
        "path": "/javascript-type-system/"
    },
    {
        "componentChunkName": "component---src-templates-blog-post-js",
        "layout": "layout---index",
        "layoutComponentChunkName": "component---src-layouts-index-js",
        "jsonName": "gradient-coin-tutorial.json",
        "path": "/gradient-coin-tutorial/"
    },
    {
        "componentChunkName": "component---src-templates-blog-post-js",
        "layout": "layout---index",
        "layoutComponentChunkName": "component---src-layouts-index-js",
        "jsonName": "firebase-react-tutorial.json",
        "path": "/firebase-react-tutorial/"
    },
    {
        "componentChunkName": "component---src-templates-blog-post-js",
        "layout": "layout---index",
        "layoutComponentChunkName": "component---src-layouts-index-js",
        "jsonName": "quick-voronoi-example.json",
        "path": "/quick-voronoi-example/"
    },
    {
        "componentChunkName": "component---src-templates-blog-post-js",
        "layout": "layout---index",
        "layoutComponentChunkName": "component---src-layouts-index-js",
        "jsonName": "ethereum-react-dapp-tutorial-part-2.json",
        "path": "/ethereum-react-dapp-tutorial-part-2/"
    },
    {
        "componentChunkName": "component---src-templates-blog-post-js",
        "layout": "layout---index",
        "layoutComponentChunkName": "component---src-layouts-index-js",
        "jsonName": "ethereum-react-dapp-tutorial.json",
        "path": "/ethereum-react-dapp-tutorial/"
    },
    {
        "componentChunkName": "component---src-templates-blog-post-js",
        "layout": "layout---index",
        "layoutComponentChunkName": "component---src-layouts-index-js",
        "jsonName": "react-native-mobx-tutorial-part-2.json",
        "path": "/react-native-mobx-tutorial-part-2/"
    },
    {
        "componentChunkName": "component---src-templates-blog-post-js",
        "layout": "layout---index",
        "layoutComponentChunkName": "component---src-layouts-index-js",
        "jsonName": "react-native-mobx-tutorial.json",
        "path": "/react-native-mobx-tutorial/"
    },
    {
        "componentChunkName": "component---src-templates-blog-post-js",
        "layout": "layout---index",
        "layoutComponentChunkName": "component---src-layouts-index-js",
        "jsonName": "react-native-e-2-e-tests-with-detox.json",
        "path": "/react-native-e2e-tests-with-detox/"
    },
    {
        "componentChunkName": "component---src-templates-blog-post-js",
        "layout": "layout---index",
        "layoutComponentChunkName": "component---src-layouts-index-js",
        "jsonName": "reducers-vs-transducers.json",
        "path": "/reducers-vs-transducers/"
    },
    {
        "componentChunkName": "component---src-templates-blog-post-js",
        "layout": "layout---index",
        "layoutComponentChunkName": "component---src-layouts-index-js",
        "jsonName": "why-you-should-use-transform-class-properties-plugin.json",
        "path": "/why-you-should-use-transform-class-properties-plugin/"
    },
    {
        "componentChunkName": "component---src-templates-blog-post-js",
        "layout": "layout---index",
        "layoutComponentChunkName": "component---src-layouts-index-js",
        "jsonName": "react-modal-window.json",
        "path": "/react-modal-window/"
    },
    {
        "componentChunkName": "component---src-templates-blog-post-js",
        "layout": "layout---index",
        "layoutComponentChunkName": "component---src-layouts-index-js",
        "jsonName": "open-closed-principle.json",
        "path": "/open-closed-principle/"
    },
    {
        "componentChunkName": "component---src-templates-blog-post-js",
        "layout": "layout---index",
        "layoutComponentChunkName": "component---src-layouts-index-js",
        "jsonName": "dont-mock-what-you-dont-own.json",
        "path": "/dont-mock-what-you-dont-own/"
    },
    {
        "componentChunkName": "component---src-templates-blog-post-js",
        "layout": "layout---index",
        "layoutComponentChunkName": "component---src-layouts-index-js",
        "jsonName": "liskov-substitution-principle.json",
        "path": "/liskov-substitution-principle/"
    },
    {
        "componentChunkName": "component---src-templates-blog-post-js",
        "layout": "layout---index",
        "layoutComponentChunkName": "component---src-layouts-index-js",
        "jsonName": "basic-karma-js.json",
        "path": "/basic-karma-js/"
    },
    {
        "componentChunkName": "component---src-templates-blog-post-js",
        "layout": "layout---index",
        "layoutComponentChunkName": "component---src-layouts-index-js",
        "jsonName": "git-add-patch.json",
        "path": "/git-add-patch/"
    },
    {
        "componentChunkName": "component---src-templates-blog-post-js",
        "layout": "layout---index",
        "layoutComponentChunkName": "component---src-layouts-index-js",
        "jsonName": "skills-of-an-effective-developer.json",
        "path": "/skills-of-an-effective-developer/"
    },
    {
        "componentChunkName": "component---src-templates-blog-post-js",
        "layout": "layout---index",
        "layoutComponentChunkName": "component---src-layouts-index-js",
        "jsonName": "getting-schwifty-with-pull-requests.json",
        "path": "/getting-schwifty-with-pull-requests/"
    },
    {
        "componentChunkName": "component---src-templates-blog-post-js",
        "layout": "layout---index",
        "layoutComponentChunkName": "component---src-layouts-index-js",
        "jsonName": "magical-mystery-guide-for-async-await-in-javascript.json",
        "path": "/magical-mystery-guide-for-async-await-in-javascript/"
    },
    {
        "componentChunkName": "component---cache-dev-404-page-js",
        "layout": "layout---index",
        "layoutComponentChunkName": "component---src-layouts-index-js",
        "jsonName": "dev-404-page.json",
        "path": "/dev-404-page/"
    },
    {
        "componentChunkName": "component---src-pages-404-js",
        "layout": "layout---index",
        "layoutComponentChunkName": "component---src-layouts-index-js",
        "jsonName": "404.json",
        "path": "/404/"
    },
    {
        "componentChunkName": "component---src-pages-index-js",
        "layout": "layout---index",
        "layoutComponentChunkName": "component---src-layouts-index-js",
        "jsonName": "index.json",
        "path": "/"
    },
    {
        "componentChunkName": "component---src-pages-404-js",
        "layout": "layout---index",
        "layoutComponentChunkName": "component---src-layouts-index-js",
        "jsonName": "404-html.json",
        "path": "/404.html"
    }
]